{"note":"This file is an internal implementation detail to speed up HTML report generation. Its format can change at any time. You might be looking for the JSON report: https://coverage.rtfd.io/cmd.html#cmd-json","format":5,"version":"7.5.1","globals":"4e5629a1aa7123cdc150877d20b18017","files":{"main_py":{"hash":"5fce7ce9bb1a7621ef54855748808442","index":{"url":"main_py.html","file":"main.py","description":"","nums":{"precision":0,"n_files":1,"n_statements":117,"n_excluded":0,"n_missing":95,"n_branches":0,"n_partial_branches":0,"n_missing_branches":0}}},"test_Addition_py":{"hash":"7be6a57567f283926bb8ee170c9b3219","index":{"url":"test_Addition_py.html","file":"test_Addition.py","description":"","nums":{"precision":0,"n_files":1,"n_statements":57,"n_excluded":0,"n_missing":51,"n_branches":0,"n_partial_branches":0,"n_missing_branches":0}}},"test_Average_py":{"hash":"1e167bbd59e0ad84c60abdc1f1be242c","index":{"url":"test_Average_py.html","file":"test_Average.py","description":"","nums":{"precision":0,"n_files":1,"n_statements":72,"n_excluded":0,"n_missing":68,"n_branches":0,"n_partial_branches":0,"n_missing_branches":0}}},"test_Binomial_py":{"hash":"d751d6613cbe9ab219ea05a49022c861","index":{"url":"test_Binomial_py.html","file":"test_Binomial.py","description":"","nums":{"precision":0,"n_files":1,"n_statements":71,"n_excluded":0,"n_missing":65,"n_branches":0,"n_partial_branches":0,"n_missing_branches":0}}},"test_ComplexArithmetic_py":{"hash":"f58827f1e004138ffbec38ff33e43edf","index":{"url":"test_ComplexArithmetic_py.html","file":"test_ComplexArithmetic.py","description":"","nums":{"precision":0,"n_files":1,"n_statements":105,"n_excluded":0,"n_missing":0,"n_branches":0,"n_partial_branches":0,"n_missing_branches":0}}},"test_Division_py":{"hash":"eafa8da0b67531219efc456166cec16f","index":{"url":"test_Division_py.html","file":"test_Division.py","description":"","nums":{"precision":0,"n_files":1,"n_statements":84,"n_excluded":0,"n_missing":79,"n_branches":0,"n_partial_branches":0,"n_missing_branches":0}}},"test_Factorial_py":{"hash":"0e2e845e613bf2f7dc34ad42bff6a40b","index":{"url":"test_Factorial_py.html","file":"test_Factorial.py","description":"","nums":{"precision":0,"n_files":1,"n_statements":44,"n_excluded":0,"n_missing":40,"n_branches":0,"n_partial_branches":0,"n_missing_branches":0}}},"test_Multiplication_py":{"hash":"a5378d496d64c05f127b02427d3109ab","index":{"url":"test_Multiplication_py.html","file":"test_Multiplication.py","description":"","nums":{"precision":0,"n_files":1,"n_statements":72,"n_excluded":0,"n_missing":67,"n_branches":0,"n_partial_branches":0,"n_missing_branches":0}}},"test_Subtraction_py":{"hash":"6d5cdb930c0a401fa11b437eae8b85b5","index":{"url":"test_Subtraction_py.html","file":"test_Subtraction.py","description":"","nums":{"precision":0,"n_files":1,"n_statements":74,"n_excluded":0,"n_missing":71,"n_branches":0,"n_partial_branches":0,"n_missing_branches":0}}}}}